discoverable_garage_door/.config.yaml
discoverable_garage_door/__init__.py
discoverable_garage_door/__main__.py
discoverable_garage_door/config.py
discoverable_garage_door/contacts.py
discoverable_garage_door/cover.py
discoverable_garage_door/door.py
discoverable_garage_door/gpio.py
discoverable_garage_door/logging.conf
discoverable_garage_door/util.py
discoverable_garage_door-0.1.4.dist-info/LICENSE
discoverable_garage_door-0.1.4.dist-info/METADATA
discoverable_garage_door-0.1.4.dist-info/WHEEL
discoverable_garage_door-0.1.4.dist-info/RECORD
