Metadata-Version: 2.1
Name: discoverable-garage-door
Version: 0.1.4
Summary: 
Author: Tim Daley
Author-email: timdaley@earthling.net
Requires-Python: >=3.11,<4.0
Classifier: Programming Language :: Python :: 3
Classifier: Programming Language :: Python :: 3.11
Requires-Dist: ha-mqtt-discoverable (>=0.9.0,<0.10.0)
Requires-Dist: pydantic-yaml (>=0.11.2,<0.12.0)
Requires-Dist: toml (>=0.10.2,<0.11.0)
